firefox_downloader/__init__.py
firefox_downloader/__main__.py
firefox_downloader/current.py
firefox_downloader/info.py
firefox_downloader/remote.py
firefox_downloader/utils.py
firefox_downloader/config/__init__.py
firefox_downloader/config/desktop_file.py
firefox_downloader-0.1.4.data/scripts/firefox_downloader
firefox_downloader-0.1.4.dist-info/METADATA
firefox_downloader-0.1.4.dist-info/WHEEL
firefox_downloader-0.1.4.dist-info/top_level.txt
firefox_downloader-0.1.4.dist-info/RECORD
